ondine_laser_control/__init__.py
ondine_laser_control/calibration.py
ondine_laser_control/calibration_server.py
ondine_laser_control/laser.py
ondine_laser_control/test_protocol.py
ondine_laser_control-0.1.28.dist-info/METADATA
ondine_laser_control-0.1.28.dist-info/WHEEL
ondine_laser_control-0.1.28.dist-info/top_level.txt
ondine_laser_control-0.1.28.dist-info/RECORD
