Metadata-Version: 2.1
Name: ondine-laser-control
Version: 0.1.28
Summary: Control laser attachment on OpenTrons robot
Home-page: UNKNOWN
Author: Caden Keese
Author-email: ckeese@ondinebio.com
License: MIT
Platform: UNKNOWN
